langchain_anthropic/__init__.py
langchain_anthropic/chat_models.py
langchain_anthropic/experimental.py
langchain_anthropic/llms.py
langchain_anthropic/output_parsers.py
langchain_anthropic/py.typed
langchain_anthropic-0.2.2.dist-info/LICENSE
langchain_anthropic-0.2.2.dist-info/METADATA
langchain_anthropic-0.2.2.dist-info/WHEEL
langchain_anthropic-0.2.2.dist-info/RECORD
