Metadata-Version: 2.1
Name: langchain-anthropic
Version: 0.2.2
Summary: An integration package connecting AnthropicMessages and LangChain
Home-page: https://github.com/langchain-ai/langchain
License: MIT
Requires-Python: >=3.9,<4.0
Classifier: License :: OSI Approved :: MIT License
Classifier: Programming Language :: Python :: 3
Classifier: Programming Language :: Python :: 3.9
Classifier: Programming Language :: Python :: 3.10
Classifier: Programming Language :: Python :: 3.11
Classifier: Programming Language :: Python :: 3.12
Requires-Dist: anthropic (>=0.30.0,<1)
Requires-Dist: defusedxml (>=0.7.1,<0.8.0)
Requires-Dist: langchain-core (>=0.3.9,<0.4.0)
Requires-Dist: pydantic (>=2.7.4,<3.0.0)
Project-URL: Repository, https://github.com/langchain-ai/langchain
Project-URL: Release Notes, https://github.com/langchain-ai/langchain/releases?q=tag%3A%22langchain-anthropic%3D%3D0%22&expanded=true
Project-URL: Source Code, https://github.com/langchain-ai/langchain/tree/master/libs/partners/anthropic
